{"__type__":"cc.JsonAsset","_name":"food","json":[{"ID":6000,"Icons":["shiwu_pisa_1.png","shiwu_pisa_2.png","shiwu_pisa_3.png","shiwu_pisa_4.png","shiwu_pisa_5.png"],"Type":105},{"ID":6001,"Icons":["shiwu_miaotiao_1.png","shiwu_miaotiao_2.png","shiwu_miaotiao_3.png","shiwu_miaotiao_4.png","shiwu_miaotiao_5.png"],"Type":105},{"ID":6002,"Icons":["shiwu_dangao_1.png","shiwu_dangao_2.png","shiwu_dangao_3.png","shiwu_dangao_4.png","shiwu_dangao_5.png"],"Type":105},{"ID":6003,"Icons":["shiwu_tiantianquan_1.png","shiwu_tiantianquan_2.png","shiwu_tiantianquan_3.png","shiwu_tiantianquan_4.png","shiwu_tiantianquan_5.png"],"Type":105},{"ID":6004,"Icons":["shiwu_shousi_1.png","shiwu_shousi_2.png","shiwu_shousi_3.png","shiwu_shousi_4.png","shiwu_shousi_5.png"],"Type":105},{"ID":6005,"Icons":["shiwu_hanbao_1.png","shiwu_hanbao_2.png","shiwu_hanbao_3.png","shiwu_hanbao_4.png","shiwu_hanbao_5.png"],"Type":105},{"ID":6006,"Icons":["shiwu_mianbao_1.png","shiwu_mianbao_2.png","shiwu_mianbao_3.png","shiwu_mianbao_4.png","shiwu_mianbao_5.png"],"Type":105},{"ID":6007,"Icons":["shiwu_dan_1.png","shiwu_dan_2.png","shiwu_dan_3.png","shiwu_dan_4.png","shiwu_dan_5.png"],"Type":105},{"ID":6008,"Icons":["shiwu_niunai_1.png","shiwu_niunai_2.png","shiwu_niunai_3.png","shiwu_niunai_4.png","shiwu_niunai_5.png"],"Type":105},{"ID":6009,"Icons":["shiwu_guozhi_1.png","shiwu_guozhi_2.png","shiwu_guozhi_3.png","shiwu_guozhi_4.png","shiwu_guozhi_5.png"],"Type":105},{"ID":6010,"Icons":["shiwu_kafei_1.png","shiwu_kafei_2.png","shiwu_kafei_3.png","shiwu_kafei_4.png","shiwu_kafei_5.png"],"Type":105},{"ID":6011,"Icons":["shiwu_kuangquanshui_1.png","shiwu_kuangquanshui_2.png","shiwu_kuangquanshui_3.png","shiwu_kuangquanshui_4.png","shiwu_kuangquanshui_5.png"],"Type":105},{"ID":6012,"Icons":["shiwu_guantou_1.png","shiwu_guantou_2.png","shiwu_guantou_3.png","shiwu_guantou_4.png","shiwu_guantou_5.png"],"Type":105},{"ID":6013,"Icons":["shiwu_xiangchang_1.png","shiwu_xiangchang_2.png","shiwu_xiangchang_3.png","shiwu_xiangchang_4.png","shiwu_xiangchang_5.png"],"Type":105},{"ID":6014,"Icons":["shiwu_sela_1.png","shiwu_sela_2.png","shiwu_sela_3.png","shiwu_sela_4.png","shiwu_sela_5.png"],"Type":105},{"ID":6015,"Icons":["shiwu_rou_1.png","shiwu_rou_2.png","shiwu_rou_3.png","shiwu_rou_4.png","shiwu_rou_5.png"],"Type":105},{"ID":6016,"Icons":["shiwu_bingqilin_1.png","shiwu_bingqilin_2.png","shiwu_bingqilin_3.png","shiwu_bingqilin_4.png","shiwu_bingqilin_5.png"],"Type":105},{"ID":6017,"Icons":["shiwu_tang_1.png","shiwu_tang_2.png","shiwu_tang_3.png","shiwu_tang_4.png","shiwu_tang_5.png"],"Type":105},{"ID":6018,"Icons":["shiwu_qiaokeli_1.png","shiwu_qiaokeli_2.png","shiwu_qiaokeli_3.png","shiwu_qiaokeli_4.png","shiwu_qiaokeli_5.png"],"Type":105},{"ID":6019,"Icons":["shiwu_shutiao_1.png","shiwu_shutiao_2.png","shiwu_shutiao_3.png","shiwu_shutiao_4.png","shiwu_shutiao_5.png"],"Type":105}]}