{
    "gamePath": "games/",
    "normalPath": "games/normal/",
    "specialPath": "games/special/",
    "Url": "https://vicat.wang/GameRes/",
    "normalGames": [
        "DaubCash",
        "Bust-A-Move-CheckN",
        "Bust-A-Move",
        "BubbleGold",
        "SolitaireWin",
        "SolitaireWin-Easy",
        "SolitaireWin-ad",
        "21-Cash-ad",
        "21-Cash",
        "21-Cash-Easy",
        "SpiderRush",
        "CubeMatrix",
        "FruitPunch",
        "FruitPunch-ad",
        "PunchToTheMoon",
        "MonsterBall",
        "FishJump"
    ],
    "specialGames": [
        "DaubCash",
        "Bust-A-Move-CheckN",
        "Bust-A-Move",
        "BubbleGold",
        "SolitaireWin",
        "SolitaireWin-Easy",
        "SolitaireWin-ad",
        "21-Cash-ad",
        "21-Cash",
        "21-Cash-Easy",
        "SpiderRush",
        "FruitPunch-ad",
        "FishJump"
    ],
    "nativeGames": [
        "DaubCash"
    ],
    "new": ["DaubCash", "Bust-A-Move-CheckN"]

}