[{"__type__":"cc.Prefab","_name":"Effect.10","data":{"__id__":1}},{"__type__":"cc.Node","_name":"Effect","_components":[{"__type__":"cc.Sprite","node":{"__id__":1},"_materials":[{"__uuid__":"ecpdLyjvZBwrvm+cedCcQy"}],"_sizeMode":2,"_isTrimmedMode":false},{"__type__":"6e7abVPhg9KJ5CuC+I+KC79","node":{"__id__":1},"Frames":{"__uuid__":"d8oVCqXOVLV6narwFOYkT+"}},{"__type__":"9d18e8rt7BPM4oVAhnYcbc9","node":{"__id__":1},"Frames":{"__uuid__":"d8oVCqXOVLV6narwFOYkT+"},"PrefixName":"ae_leaf","FrameCount":6},{"__type__":"654a2LBIdJPdb3NSUS/lOeo","node":{"__id__":1},"Frames":{"__uuid__":"d8oVCqXOVLV6narwFOYkT+"},"PrefixName":"ae_mud","FrameCount":6},{"__type__":"55740DyeqNL4KgOVFGSlQmZ","node":{"__id__":1},"Frames":{"__uuid__":"d8oVCqXOVLV6narwFOYkT+"},"PrefixName":"ae_stone","FrameCount":6},{"__type__":"1652apF4FZFmYJ33HhpO22S","node":{"__id__":1},"Frames":{"__uuid__":"d8oVCqXOVLV6narwFOYkT+"},"PrefixName":"ae_wood","FrameCount":6},{"__type__":"2b7adaChfhI9rYGtLLJ5Ii0","node":{"__id__":1},"Frames":{"__uuid__":"d8oVCqXOVLV6narwFOYkT+"},"PrefixName":"ae_line","FrameCount":9},{"__type__":"009722VdURCBKr/u5er1+8S","node":{"__id__":1},"Frames":{"__uuid__":"d8oVCqXOVLV6narwFOYkT+"},"PrefixName":"ae_merge_spe","FrameCount":6},{"__type__":"bb1e90nZJFCDL9epNNbtguq","node":{"__id__":1},"Frames":{"__uuid__":"d8oVCqXOVLV6narwFOYkT+"},"PrefixName":"ae_dispear_rainbow","FrameCount":2}],"_prefab":{"__type__":"cc.PrefabInfo","root":{"__id__":1},"asset":{"__uuid__":"22iL1NTeJDf7RtrJ+UBaxy"},"fileId":"23U/9pcqxJg57FNX1ttiUN"},"_contentSize":{"__type__":"cc.Size","width":292,"height":60},"_trs":{"__type__":"TypedArray","ctor":"Float64Array","array":[-3.474,-41.686,0,0,0,0,1,1,1,1]}}]